prometa/__init__.py
prometa/citation.py
prometa/common.py
prometa/config.py
prometa/exception.py
prometa/file.py
prometa/insert.py
prometa/main.py
prometa/project.py
prometa/readme.py
prometa/requests.py
prometa/utils.py
prometa/version.py
prometa/codemeta/__init__.py
prometa/codemeta/codemeta.py
prometa/git/__init__.py
prometa/git/host.py
prometa/git/repo.py
prometa/git/gitlab/__init__.py
prometa/git/gitlab/api.py
prometa/git/gitlab/host.py
prometa/git/gitlab/badges/__init__.py
prometa/git/gitlab/badges/badge_manager.py
prometa/git/gitlab/badges/common.py
prometa/git/gitlab/badges/latest_release.py
prometa/git/gitlab/badges/license.py
prometa/git/gitlab/badges/pipeline_status.py
prometa/git/gitlab/badges/test_coverage.py
prometa/git/gitlab/badges/python/__init__.py
prometa/git/gitlab/badges/python/black.py
prometa/git/gitlab/badges/python/hatch.py
prometa/git/gitlab/badges/python/isort.py
prometa/git/gitlab/badges/python/pylint.py
prometa/git/gitlab/badges/python/pypi.py
prometa/git/gitlab/badges/python/pypi_downloads.py
prometa/git/gitlab/badges/python/python.py
prometa/git/gitlab/ci/__init__.py
prometa/git/gitlab/ci/ci_job_manager.py
prometa/git/gitlab/ci/pages.py
prometa/git/gitlab/ci/release_job.py
prometa/git/gitlab/ci/python/__init__.py
prometa/git/gitlab/ci/python/pylint.py
prometa/git/gitlab/ci/python/register_python_package.py
prometa/git/gitlab/hooks/__init__.py
prometa/git/gitlab/hooks/hook_manager.py
prometa/git/gitlab/hooks/software_heritage.py
prometa/id/__init__.py
prometa/id/hal.py
prometa/id/orcid.py
prometa/id/swh.py
prometa/package/__init__.py
prometa/package/package.py
prometa/package/python/__init__.py
prometa/package/python/codemeta.py
prometa/package/python/package.py
prometa/python/__init__.py
prometa/python/common.py
prometa/python/venv.py
prometa/scripts/__init__.py
prometa/scripts/document_gitlab_badges.py
prometa/scripts/document_gitlab_ci_jobs.py
prometa/scripts/document_gitlab_hooks.py
prometa/scripts/document_labels.py
prometa-2025.16.dist-info/METADATA
prometa-2025.16.dist-info/WHEEL
prometa-2025.16.dist-info/entry_points.txt
prometa-2025.16.dist-info/licenses/LICENSE.txt
prometa-2025.16.dist-info/RECORD
