Metadata-Version: 2.4
Name: Prometa
Version: 2025.16
Summary: Manage project metadata.
Project-URL: Homepage, https://gitlab.inria.fr/jrye/prometa
Project-URL: Source, https://gitlab.inria.fr/jrye/prometa.git
Project-URL: Documentation, https://jrye.gitlabpages.inria.fr/prometa
Project-URL: Issues, https://gitlab.inria.fr/jrye/prometa/issues
Author-email: Jan-Michael Rye <jan-michael.rye@inria.fr>
License: MIT License
License-File: LICENSE.txt
Classifier: License :: OSI Approved :: MIT License
Classifier: Operating System :: OS Independent
Classifier: Programming Language :: Python :: 3
Requires-Python: >=3.6
Requires-Dist: codemetapy
Requires-Dist: jrai-common-mixins
Requires-Dist: python-gitlab
Requires-Dist: pyxdg
Requires-Dist: pyyaml
Requires-Dist: requests
Requires-Dist: spdx-license-list
Requires-Dist: spdx-matcher
Requires-Dist: tomli-w
Requires-Dist: trove-classifiers
